cogents_smith/__init__.py
cogents_smith/groups.py
cogents_smith/py.typed
cogents_smith/agents/askura_agent/README.md
cogents_smith/agents/askura_agent/__init__.py
cogents_smith/agents/askura_agent/askura_agent.py
cogents_smith/agents/askura_agent/conversation.py
cogents_smith/agents/askura_agent/extractor.py
cogents_smith/agents/askura_agent/memory.py
cogents_smith/agents/askura_agent/models.py
cogents_smith/agents/askura_agent/prompts.py
cogents_smith/agents/askura_agent/reflection.py
cogents_smith/agents/askura_agent/summarizer.py
cogents_smith/agents/askura_agent/utils.py
cogents_smith/agents/seekra_agent/README.md
cogents_smith/agents/seekra_agent/__init__.py
cogents_smith/agents/seekra_agent/configuration.py
cogents_smith/agents/seekra_agent/prompts.py
cogents_smith/agents/seekra_agent/researcher.py
cogents_smith/agents/seekra_agent/schemas.py
cogents_smith/agents/seekra_agent/state.py
cogents_smith/toolkits/__init__.py
cogents_smith/toolkits/arxiv_toolkit.py
cogents_smith/toolkits/audio_aliyun_toolkit.py
cogents_smith/toolkits/audio_toolkit.py
cogents_smith/toolkits/bash_toolkit.py
cogents_smith/toolkits/document_toolkit.py
cogents_smith/toolkits/file_edit_toolkit.py
cogents_smith/toolkits/github_toolkit.py
cogents_smith/toolkits/gmail_toolkit.py
cogents_smith/toolkits/image_toolkit.py
cogents_smith/toolkits/memory_toolkit.py
cogents_smith/toolkits/python_executor_toolkit.py
cogents_smith/toolkits/search_toolkit.py
cogents_smith/toolkits/serper_toolkit.py
cogents_smith/toolkits/tabular_data_toolkit.py
cogents_smith/toolkits/user_interaction_toolkit.py
cogents_smith/toolkits/video_toolkit.py
cogents_smith/toolkits/wikipedia_toolkit.py
cogents_smith-0.2.0.dist-info/licenses/LICENSE
cogents_smith-0.2.0.dist-info/METADATA
cogents_smith-0.2.0.dist-info/WHEEL
cogents_smith-0.2.0.dist-info/top_level.txt
cogents_smith-0.2.0.dist-info/RECORD
